nina_helper/__init__.py
nina_helper/nina_helper.py
nina_helper-2.4.dist-info/DESCRIPTION.rst
nina_helper-2.4.dist-info/METADATA
nina_helper-2.4.dist-info/RECORD
nina_helper-2.4.dist-info/WHEEL
nina_helper-2.4.dist-info/metadata.json
nina_helper-2.4.dist-info/top_level.txt
