Metadata-Version: 2.0
Name: nina-helper
Version: 2.4
Summary: Utiltiy functions for workign on the NinaPro Databases (1 & 2)
Home-page: https://github.com/Lif3line/nina_helper_package_mk2
Author: Lif3line
Author-email: adamhartwell2@gmail.com
License: MIT
Keywords: ninapro emg
Platform: UNKNOWN
Requires-Dist: numpy
Requires-Dist: scipy
Requires-Dist: sklearn
